setup.py
ScoreiT/__init__.py
ScoreiT.egg-info/PKG-INFO
ScoreiT.egg-info/SOURCES.txt
ScoreiT.egg-info/dependency_links.txt
ScoreiT.egg-info/requires.txt
ScoreiT.egg-info/top_level.txt
ScoreiT.egg-info/zip-safe
src/ScoreiT