Metadata-Version: 1.0
Name: ScoreiT
Version: 1.0
Summary: cricket score notifier
Home-page: https://github.com/DeveshAgrawal1/ScoreiT
Author: Devesh Agrawal
Author-email: dagrawal1096@gmail.com
License: MIT
Keywords: cricket, score, , , 
Platform: UNKNOWN
